{
  "collection": {
    "info": {
      "_postman_id": "8ce11389-4715-4913-ac8a-339aceeb0d65",
      "name": "Credentials Revocation Tutorial",
      "schema": "https://schema.getpostman.com/json/collection/v2.1.0/collection.json"
    },
    "item": [
      {
        "id": "d0fd291d-88d9-43db-b157-ad3b4afc90b7",
        "name": "Get Access Token",
        "request": {
          "url": {
            "host": [
              "{{TOKEN_ENDPOINT}}"
            ],
            "query": [],
            "variable": []
          },
          "method": "POST",
          "body": {
            "mode": "urlencoded",
            "urlencoded": [
              {
                "key": "audience",
                "value": "{{TOKEN_AUDIENCE}}"
              },
              {
                "key": "client_id",
                "value": "{{CLIENT_ID}}"
              },
              {
                "key": "client_secret",
                "value": "{{CLIENT_SECRET}}"
              },
              {
                "key": "grant_type",
                "value": "client_credentials"
              },
              {
                "key": "scope",
                "value": "{{CLIENT_SCOPE}}"
              }
            ]
          }
        },
        "response": [],
        "event": [
          {
            "listen": "test",
            "script": {
              "id": "0595d98c-2d2a-4a87-8bab-f63907ef2e58",
              "type": "text/javascript",
              "exec": [
                "// Token requests are expected to return a `200 Success` response code. Any",
                "// other response code should trigger a failure.",
                "pm.test(\"must return `200 Success` status\", function() {",
                "    pm.response.to.have.status(200);",
                "});",
                "",
                "// The response should include an `access_token` value - this will be presented",
                "// to authenticated API endpoints in the `Authentication` header (see the last",
                "// testing code block for details on how this is persisted).",
                "pm.test(\"response body must include non-empty access_token\", function () {",
                "    const { access_token } = pm.response.json()",
                "    pm.expect(access_token).to.be.a('string').that.is.not.empty;",
                "});",
                "",
                "// The type of `access_token` returned by the token request is expected to be",
                "// `Bearer`.",
                "pm.test(\"response body must represent `Bearer` token\", function() {",
                "    const { token_type } = pm.response.json()",
                "    pm.expect(token_type).to.equal(\"Bearer\");",
                "});",
                "",
                "// The returned data includes an `expires_in` field that indicates time until",
                "// token expiration. Validate that this value is a whole number greater than",
                "// zero, as anything less than or equal to zero means that the `access_token`",
                "// is already expired.",
                "pm.test(\"returned token must expire in the future\", function() {",
                "    const { expires_in } = pm.response.json()",
                "    pm.expect(expires_in).to.be.above(0);",
                "});",
                "",
                "// The returned `access_token` value is persisted as a Postman collection",
                "// variable that can be accessed by other requests in the collection by calling",
                "// `pm.collectionVariables.get(\"access_token\")`.",
                "pm.test(\"`access_token` persisted to collectionVariables\", function() {",
                "    const { access_token } = pm.response.json()",
                "    pm.collectionVariables.set(\"access_token\", access_token);",
                "});"
              ],
              "_lastExecutionId": "a53b6733-52a9-4835-9285-db821845ea02"
            }
          }
        ]
      },
      {
        "id": "d7310909-ab8c-4ae0-95bc-ea888b7ae463",
        "name": "Get Organization DIDs",
        "request": {
          "url": {
            "path": [
              "identifiers",
              "{{ORGANIZATION_DID_WEB}}"
            ],
            "host": [
              "{{API_BASE_URL}}"
            ],
            "query": [],
            "variable": []
          },
          "header": [
            {
              "key": "Accept",
              "value": "application/json"
            }
          ],
          "method": "GET",
          "auth": {
            "type": "bearer",
            "bearer": [
              {
                "type": "string",
                "value": "{{access_token}}",
                "key": "token"
              }
            ]
          }
        },
        "response": [],
        "event": [
          {
            "listen": "test",
            "script": {
              "id": "0a0d6bcb-c6be-4cea-ac8f-d3284a2fc255",
              "type": "text/javascript",
              "exec": [
                "// This endpoint is authenticated. This test will not prevent the request from",
                "// running when the `access_token` collection variable is missing, but it will",
                "// give an indication of why the request failed in that scenario.",
                "pm.test(\"`access_token` collection variable must be set\", function () {",
                "    const access_token = pm.collectionVariables.get(\"access_token\");",
                "    pm.expect(access_token).to.be.a('string').that.is.not.empty;",
                "});",
                "",
                "pm.test(\"Status code is 200\", function () {",
                "    pm.response.to.have.status(200);",
                "});",
                "",
                "pm.test(\"must include valid JSON response body\", function() {",
                "    pm.response.json(); // will throw on parse failure",
                "});",
                "",
                "// The response JSON must include a didDocument property that contains the",
                "// resolved DID document.",
                "pm.test(\"didDocument must be present in response body\", function() {",
                "    const jsonData = pm.response.json();",
                "    pm.expect(jsonData).to.have.property('didDocument');",
                "});",
                "",
                "// If a verificationMethod property is present, the controller property must",
                "// match the didDocument.id property.",
                "pm.test(\"verification method controller must match did subject\", function() {",
                "    const { didDocument } = pm.response.json();",
                "    const vm = didDocument.verificationMethod || [];",
                "    vm.forEach((m) => pm.expect(m.controller).to.equal(didDocument.id));",
                "});",
                "",
                "// The value of didDocument.id is persisted as a Postman collection variable",
                "// that can be accessed by other requests in the collection by calling",
                "// pm.collectionVariables.get(\"credential_issuer_id\").",
                "pm.test(\"`credential_issuer_id` persisted to collectionVariables\", function() {",
                "    const { didDocument } = pm.response.json();",
                "    pm.collectionVariables.set(\"credential_issuer_id\", didDocument.id);",
                "});"
              ],
              "_lastExecutionId": "f022ecd5-d3b1-4527-8f59-9d8d991a644a"
            }
          }
        ],
        "protocolProfileBehavior": {
          "disabledSystemHeaders": {}
        }
      },
      {
        "id": "562681d6-f1ff-44ba-a203-9d4ea775adf1",
        "name": "Issue Credential",
        "request": {
          "url": {
            "path": [
              "credentials",
              "issue"
            ],
            "host": [
              "{{API_BASE_URL}}"
            ],
            "query": [],
            "variable": []
          },
          "header": [
            {
              "key": "Accept",
              "value": "application/vc+ld+json"
            }
          ],
          "method": "POST",
          "body": {
            "mode": "raw",
            "raw": "{\n    \"credential\": {\n        \"@context\": [\n            \"https://www.w3.org/2018/credentials/v1\",\n            \"https://w3id.org/vc-revocation-list-2020/v1\"\n        ],\n        \"id\": \"urn:uuid:{{$randomUUID}}\",\n        \"type\": [\n            \"VerifiableCredential\"\n        ],\n        \"issuer\": \"{{credential_issuer_id}}\",\n        \"issuanceDate\": \"{{$isoTimestamp}}\",\n        \"credentialSubject\": {\n            \"id\": \"did:example:123\"\n        }\n    },\n    \"options\": {\n        \"type\": \"Ed25519Signature2018\",\n        \"created\": \"{{$isoTimestamp}}\",\n        \"credentialStatus\": {\n            \"type\": \"RevocationList2020Status\"\n        }\n    }\n}",
            "options": {
              "raw": {
                "language": "json"
              }
            }
          },
          "auth": {
            "type": "bearer",
            "bearer": [
              {
                "type": "string",
                "value": "{{access_token}}",
                "key": "token"
              }
            ]
          }
        },
        "response": [],
        "event": [
          {
            "listen": "test",
            "script": {
              "id": "6af2ab7c-d0a6-40a2-9959-689dfcef3dc4",
              "type": "text/javascript",
              "exec": [
                "pm.test(\"`access_token` collection variable must be set\", function () {",
                "    pm.expect(pm.collectionVariables.get(\"access_token\")).to.not.be.undefined;",
                "});",
                "",
                "pm.test(\"`credential_issuer_id` collection variable must be set\", function () {",
                "    pm.expect(pm.collectionVariables.get(\"credential_issuer_id\")).to.not.be.undefined;",
                "});",
                "",
                "pm.test(\"must return `201 Created` status\", function () {",
                "    pm.response.to.have.status(201);",
                "});",
                "",
                "// Verifiable credential must be made available to later requests",
                "pm.test(\"`verifiable_credential` persisted to collectionVariables\", function() {",
                "    const {verifiableCredential} = pm.response.json();",
                "    pm.collectionVariables.set(\"verifiable_credential\", JSON.stringify(verifiableCredential));",
                "});"
              ],
              "_lastExecutionId": "de706174-93d7-4757-9109-47ed59193155"
            }
          },
          {
            "listen": "prerequest",
            "script": {
              "id": "86cb99e7-15ac-45d0-a910-d4f062b09177",
              "type": "text/javascript",
              "exec": [
                ""
              ],
              "_lastExecutionId": "6b2bf6cc-a22f-4429-a4d0-2730f2a7677e"
            }
          }
        ]
      },
      {
        "id": "34541980-182d-4ad1-b466-0fd3b850b99d",
        "name": "Verify Credential",
        "request": {
          "url": {
            "path": [
              "credentials",
              "verify"
            ],
            "host": [
              "{{API_BASE_URL}}"
            ],
            "query": [],
            "variable": []
          },
          "header": [
            {
              "key": "Accept",
              "value": "application/json"
            }
          ],
          "method": "POST",
          "body": {
            "mode": "raw",
            "raw": "{\n    \"verifiableCredential\": {{verifiable_credential}}\n}",
            "options": {
              "raw": {
                "language": "json"
              }
            }
          },
          "auth": {
            "type": "bearer",
            "bearer": [
              {
                "type": "string",
                "value": "{{access_token}}",
                "key": "token"
              }
            ]
          }
        },
        "response": [],
        "event": [
          {
            "listen": "test",
            "script": {
              "id": "d422eedb-8b8e-4a3a-b7ec-35ee8cd6b7d2",
              "type": "text/javascript",
              "exec": [
                "// The `/credentials/verify` endpoint is authenticated. This test will not",
                "// prevent the request from running when the `access_token` collection variable",
                "// is missing, but it will give an indication of why the request failed in that",
                "// scenario.",
                "pm.test(\"`access_token` collection variable must be set\", function () {",
                "    pm.expect(pm.collectionVariables.get(\"access_token\")).to.not.be.undefined;",
                "});",
                "",
                "// The `verifiable_credential` from the \"Credentials Issue\" request is used to",
                "// populate part of the request body. If this collection variable is missing,",
                "// the request will not be prevented, but this test will raise an error that",
                "// will help to identify the problem.",
                "pm.test(\"`verifiable_credential` collection variable must be set\", function () {",
                "    pm.expect(pm.collectionVariables.get(\"verifiable_credential\")).to.not.be.undefined;",
                "});",
                "",
                "// The expected response code for a \"Credentials Verify\" request is",
                "// `200 Success`.",
                "pm.test(\"must return `200 Success` status\", function () {",
                "    pm.response.to.have.status(200);",
                "});",
                "",
                "// The verification should succeed.",
                "pm.test(\"verification should be successful\", function() {",
                "    const { verified } = pm.response.json()",
                "    pm.expect(verified).to.be.true;",
                "});"
              ],
              "_lastExecutionId": "efa9ad3a-886a-486a-8382-8701536a584e"
            }
          }
        ]
      },
      {
        "id": "7681cbb5-4630-40e7-8064-dfca68ff31fc",
        "name": "Revoke Credential",
        "request": {
          "url": {
            "path": [
              "credentials",
              "status"
            ],
            "host": [
              "{{API_BASE_URL}}"
            ],
            "query": [],
            "variable": []
          },
          "header": [
            {
              "key": "Accept",
              "value": "application/json"
            }
          ],
          "method": "POST",
          "body": {
            "mode": "raw",
            "raw": "{\n    \"credentialId\": \"{{verifiable_credential_id}}\",\n    \"credentialStatus\": [\n        {\n            \"type\": \"RevocationList2020Status\",\n            \"status\": \"1\"\n        }\n    ]\n}",
            "options": {
              "raw": {
                "language": "json"
              }
            }
          },
          "auth": {
            "type": "bearer",
            "bearer": [
              {
                "type": "string",
                "value": "{{access_token}}",
                "key": "token"
              }
            ]
          }
        },
        "response": [],
        "event": [
          {
            "listen": "prerequest",
            "script": {
              "id": "7c63712b-58d9-49cc-90a0-de5219a2b17a",
              "type": "text/javascript",
              "exec": [
                "// Extract credential ID from verifiable credential",
                "let verifiable_credential_id;",
                "try {",
                "    const { id } = JSON.parse(pm.collectionVariables.get(\"verifiable_credential\"));",
                "    pm.collectionVariables.set('verifiable_credential_id', id)",
                "} catch {}",
                ""
              ],
              "_lastExecutionId": "9af1847a-aacc-4634-a5a2-37cc2644364e"
            }
          },
          {
            "listen": "test",
            "script": {
              "id": "afcd38d4-0399-48b0-a695-1b6ed67eaa90",
              "type": "text/javascript",
              "exec": [
                "// The `/credentials/status` endpoint is authenticated. This test will not",
                "// prevent the request from running when the `access_token` collection variable",
                "// is missing, but it will give an indication of why the request failed in that",
                "// scenario.",
                "pm.test(\"`access_token` collection variable must be set\", function () {",
                "    pm.expect(pm.collectionVariables.get(\"access_token\")).to.not.be.undefined;",
                "});",
                "",
                "// Verifiable credential ID is a required element item used in the request body",
                "pm.test(\"`verifiable_credential_id` local variable must be set\", function () {",
                "    pm.expect(\"verifiable_credential\").to.be.a('string').that.is.not.empty;",
                "});",
                "",
                "// The expected response code for a \"Revoke Credentials\" request is `200 Success`",
                "pm.test(\"must return `200 Success` status\", function () {",
                "    pm.response.to.have.status(200);",
                "});"
              ],
              "_lastExecutionId": "a8cde732-9a65-45dd-b2db-772dded32b95"
            }
          }
        ]
      },
      {
        "id": "743b51f6-a421-4a11-b1ff-ad79ac79591e",
        "name": "Verify Revocation",
        "request": {
          "url": {
            "path": [
              "credentials",
              "verify"
            ],
            "host": [
              "{{API_BASE_URL}}"
            ],
            "query": [],
            "variable": []
          },
          "header": [
            {
              "key": "Accept",
              "value": "application/json"
            }
          ],
          "method": "POST",
          "body": {
            "mode": "raw",
            "raw": "{\n    \"verifiableCredential\": {{verifiable_credential}}\n}",
            "options": {
              "raw": {
                "language": "json"
              }
            }
          },
          "auth": {
            "type": "bearer",
            "bearer": [
              {
                "type": "string",
                "value": "{{access_token}}",
                "key": "token"
              }
            ]
          }
        },
        "response": [],
        "event": [
          {
            "listen": "test",
            "script": {
              "id": "b5516bd5-5237-4109-b14a-1155d9a71c9c",
              "type": "text/javascript",
              "exec": [
                "// The `/credentials/verify` endpoint is authenticated. This test will not",
                "// prevent the request from running when the `access_token` collection variable",
                "// is missing, but it will give an indication of why the request failed in that",
                "// scenario.",
                "pm.test(\"`access_token` collection variable must be set\", function () {",
                "    pm.expect(pm.collectionVariables.get(\"access_token\")).to.not.be.undefined;",
                "});",
                "",
                "// The `verifiable_credential` from the \"Credentials Issue\" request is used to",
                "// populate part of the request body. If this collection variable is missing,",
                "// the request will not be prevented, but this test will raise an error that",
                "// will help to identify the problem.",
                "pm.test(\"`verifiable_credential` collection variable must be set\", function () {",
                "    pm.expect(pm.collectionVariables.get(\"verifiable_credential\")).to.not.be.undefined;",
                "});",
                "",
                "// The expected response code for a \"Credentials Verify\" request is",
                "// `200 Success`.",
                "pm.test(\"must return `200 Success` status\", function () {",
                "    pm.response.to.have.status(200);",
                "});",
                "",
                "// Checks should have errors",
                "//pm.test(\"Checks should have credentialStatus errors\", function() {",
                "//    const { errors } = pm.response.json();",
                "//    pm.expect(errors).to.include(\"credentialStatus\");",
                "//});",
                "",
                "// Confirm error",
                "pm.test(\"Checks should have credentialStatus errors\", function() {",
                "    let obj = pm.response.json().verifications.find(e => e.title === \"Revocation\");",
                "    pm.expect(obj.status).to.eql(\"bad\");",
                "});",
                "",
                "",
                ""
              ],
              "_lastExecutionId": "65a83257-a726-4c29-993a-97d30766534f"
            }
          }
        ]
      }
    ]
  },
  "run": {
    "stats": {
      "iterations": {
        "total": 1,
        "pending": 0,
        "failed": 0
      },
      "items": {
        "total": 6,
        "pending": 0,
        "failed": 0
      },
      "scripts": {
        "total": 20,
        "pending": 0,
        "failed": 0
      },
      "prerequests": {
        "total": 6,
        "pending": 0,
        "failed": 0
      },
      "requests": {
        "total": 6,
        "pending": 0,
        "failed": 6
      },
      "tests": {
        "total": 6,
        "pending": 0,
        "failed": 0
      },
      "assertions": {
        "total": 26,
        "pending": 0,
        "failed": 18
      },
      "testScripts": {
        "total": 12,
        "pending": 0,
        "failed": 0
      },
      "prerequestScripts": {
        "total": 8,
        "pending": 0,
        "failed": 0
      }
    },
    "timings": {
      "responseAverage": 0,
      "responseMin": 0,
      "responseMax": 0,
      "responseSd": 0,
      "dnsAverage": 0,
      "dnsMin": 0,
      "dnsMax": 0,
      "dnsSd": 0,
      "firstByteAverage": 0,
      "firstByteMin": 0,
      "firstByteMax": 0,
      "firstByteSd": 0,
      "started": 1720830203729,
      "completed": 1720830203910
    },
    "executions": [
      {
        "id": "d0fd291d-88d9-43db-b157-ad3b4afc90b7",
        "cursor": {
          "position": 0,
          "iteration": 0,
          "length": 6,
          "cycles": 1,
          "empty": false,
          "eof": false,
          "bof": true,
          "cr": false,
          "ref": "42f37f62-8edb-4718-badf-63babd8883ff",
          "httpRequestId": "385f563a-9aca-4e78-ab5b-2a35be54f89c"
        },
        "item": {
          "id": "d0fd291d-88d9-43db-b157-ad3b4afc90b7",
          "name": "Get Access Token"
        },
        "response": {},
        "assertions": [
          {
            "assertion": "must return `200 Success` status",
            "skipped": false,
            "error": {
              "name": "AssertionError",
              "index": 0,
              "test": "must return `200 Success` status",
              "message": "expected { Object (id, _details, ...) } to have property 'code'",
              "stack": "AssertionError: expected { Object (id, _details, ...) } to have property 'code'\n   at Object.eval sandbox-script.js:1:1)"
            }
          },
          {
            "assertion": "response body must include non-empty access_token",
            "skipped": false,
            "error": {
              "name": "JSONError",
              "index": 1,
              "test": "response body must include non-empty access_token",
              "message": "Unexpected token u in JSON at position 0",
              "stack": "JSONError: Unexpected token u in JSON at position 0\n   at Object.eval sandbox-script.js:2:1)"
            }
          },
          {
            "assertion": "response body must represent `Bearer` token",
            "skipped": false,
            "error": {
              "name": "JSONError",
              "index": 2,
              "test": "response body must represent `Bearer` token",
              "message": "Unexpected token u in JSON at position 0",
              "stack": "JSONError: Unexpected token u in JSON at position 0\n   at Object.eval sandbox-script.js:3:1)"
            }
          },
          {
            "assertion": "returned token must expire in the future",
            "skipped": false,
            "error": {
              "name": "JSONError",
              "index": 3,
              "test": "returned token must expire in the future",
              "message": "Unexpected token u in JSON at position 0",
              "stack": "JSONError: Unexpected token u in JSON at position 0\n   at Object.eval sandbox-script.js:4:1)"
            }
          },
          {
            "assertion": "`access_token` persisted to collectionVariables",
            "skipped": false,
            "error": {
              "name": "JSONError",
              "index": 4,
              "test": "`access_token` persisted to collectionVariables",
              "message": "Unexpected token u in JSON at position 0",
              "stack": "JSONError: Unexpected token u in JSON at position 0\n   at Object.eval sandbox-script.js:5:1)"
            }
          }
        ]
      },
      {
        "id": "d7310909-ab8c-4ae0-95bc-ea888b7ae463",
        "cursor": {
          "ref": "6886a18e-167e-44a3-ae3e-4d5ebf7f23f9",
          "length": 6,
          "cycles": 1,
          "position": 1,
          "iteration": 0,
          "httpRequestId": "d6a4ceb9-76b1-4f78-b8dc-22becfe0535c"
        },
        "item": {
          "id": "d7310909-ab8c-4ae0-95bc-ea888b7ae463",
          "name": "Get Organization DIDs"
        },
        "response": {},
        "assertions": [
          {
            "assertion": "`access_token` collection variable must be set",
            "skipped": false,
            "error": {
              "name": "AssertionError",
              "index": 0,
              "test": "`access_token` collection variable must be set",
              "message": "expected '' not to be empty",
              "stack": "AssertionError: expected '' not to be empty\n   at Object.eval sandbox-script.js:1:2)"
            }
          },
          {
            "assertion": "Status code is 200",
            "skipped": false,
            "error": {
              "name": "AssertionError",
              "index": 1,
              "test": "Status code is 200",
              "message": "expected { Object (id, _details, ...) } to have property 'code'",
              "stack": "AssertionError: expected { Object (id, _details, ...) } to have property 'code'\n   at Object.eval sandbox-script.js:2:2)"
            }
          },
          {
            "assertion": "must include valid JSON response body",
            "skipped": false,
            "error": {
              "name": "JSONError",
              "index": 2,
              "test": "must include valid JSON response body",
              "message": "Unexpected token u in JSON at position 0",
              "stack": "JSONError: Unexpected token u in JSON at position 0\n   at Object.eval sandbox-script.js:3:2)"
            }
          },
          {
            "assertion": "didDocument must be present in response body",
            "skipped": false,
            "error": {
              "name": "JSONError",
              "index": 3,
              "test": "didDocument must be present in response body",
              "message": "Unexpected token u in JSON at position 0",
              "stack": "JSONError: Unexpected token u in JSON at position 0\n   at Object.eval sandbox-script.js:4:2)"
            }
          },
          {
            "assertion": "verification method controller must match did subject",
            "skipped": false,
            "error": {
              "name": "JSONError",
              "index": 4,
              "test": "verification method controller must match did subject",
              "message": "Unexpected token u in JSON at position 0",
              "stack": "JSONError: Unexpected token u in JSON at position 0\n   at Object.eval sandbox-script.js:5:2)"
            }
          },
          {
            "assertion": "`credential_issuer_id` persisted to collectionVariables",
            "skipped": false,
            "error": {
              "name": "JSONError",
              "index": 5,
              "test": "`credential_issuer_id` persisted to collectionVariables",
              "message": "Unexpected token u in JSON at position 0",
              "stack": "JSONError: Unexpected token u in JSON at position 0\n   at Object.eval sandbox-script.js:6:2)"
            }
          }
        ]
      },
      {
        "id": "562681d6-f1ff-44ba-a203-9d4ea775adf1",
        "cursor": {
          "ref": "007c6ca9-0795-496a-a91d-d05a36125c48",
          "length": 6,
          "cycles": 1,
          "position": 2,
          "iteration": 0,
          "httpRequestId": "330ebf18-41e8-4af2-af8b-73276c341855"
        },
        "item": {
          "id": "562681d6-f1ff-44ba-a203-9d4ea775adf1",
          "name": "Issue Credential"
        },
        "response": {},
        "assertions": [
          {
            "assertion": "`access_token` collection variable must be set",
            "skipped": false
          },
          {
            "assertion": "`credential_issuer_id` collection variable must be set",
            "skipped": false
          },
          {
            "assertion": "must return `201 Created` status",
            "skipped": false,
            "error": {
              "name": "AssertionError",
              "index": 2,
              "test": "must return `201 Created` status",
              "message": "expected { Object (id, _details, ...) } to have property 'code'",
              "stack": "AssertionError: expected { Object (id, _details, ...) } to have property 'code'\n   at Object.eval sandbox-script.js:3:3)"
            }
          },
          {
            "assertion": "`verifiable_credential` persisted to collectionVariables",
            "skipped": false,
            "error": {
              "name": "JSONError",
              "index": 3,
              "test": "`verifiable_credential` persisted to collectionVariables",
              "message": "Unexpected token u in JSON at position 0",
              "stack": "JSONError: Unexpected token u in JSON at position 0\n   at Object.eval sandbox-script.js:4:3)"
            }
          }
        ]
      },
      {
        "id": "34541980-182d-4ad1-b466-0fd3b850b99d",
        "cursor": {
          "ref": "e8c0441d-270c-486e-9fc8-8f493113043c",
          "length": 6,
          "cycles": 1,
          "position": 3,
          "iteration": 0,
          "httpRequestId": "080c4de0-19b3-4dc9-8983-06c18529622a"
        },
        "item": {
          "id": "34541980-182d-4ad1-b466-0fd3b850b99d",
          "name": "Verify Credential"
        },
        "response": {},
        "assertions": [
          {
            "assertion": "`access_token` collection variable must be set",
            "skipped": false
          },
          {
            "assertion": "`verifiable_credential` collection variable must be set",
            "skipped": false
          },
          {
            "assertion": "must return `200 Success` status",
            "skipped": false,
            "error": {
              "name": "AssertionError",
              "index": 2,
              "test": "must return `200 Success` status",
              "message": "expected { Object (id, _details, ...) } to have property 'code'",
              "stack": "AssertionError: expected { Object (id, _details, ...) } to have property 'code'\n   at Object.eval sandbox-script.js:3:4)"
            }
          },
          {
            "assertion": "verification should be successful",
            "skipped": false,
            "error": {
              "name": "JSONError",
              "index": 3,
              "test": "verification should be successful",
              "message": "Unexpected token u in JSON at position 0",
              "stack": "JSONError: Unexpected token u in JSON at position 0\n   at Object.eval sandbox-script.js:4:4)"
            }
          }
        ]
      },
      {
        "id": "7681cbb5-4630-40e7-8064-dfca68ff31fc",
        "cursor": {
          "ref": "a9809173-bb34-4d5d-a737-8527048f8437",
          "length": 6,
          "cycles": 1,
          "position": 4,
          "iteration": 0,
          "httpRequestId": "ae80268c-f3fb-44ba-8297-fc60250cf96c"
        },
        "item": {
          "id": "7681cbb5-4630-40e7-8064-dfca68ff31fc",
          "name": "Revoke Credential"
        },
        "response": {},
        "assertions": [
          {
            "assertion": "`access_token` collection variable must be set",
            "skipped": false
          },
          {
            "assertion": "`verifiable_credential_id` local variable must be set",
            "skipped": false
          },
          {
            "assertion": "must return `200 Success` status",
            "skipped": false,
            "error": {
              "name": "AssertionError",
              "index": 2,
              "test": "must return `200 Success` status",
              "message": "expected { Object (id, _details, ...) } to have property 'code'",
              "stack": "AssertionError: expected { Object (id, _details, ...) } to have property 'code'\n   at Object.eval sandbox-script.js:3:5)"
            }
          }
        ]
      },
      {
        "id": "743b51f6-a421-4a11-b1ff-ad79ac79591e",
        "cursor": {
          "ref": "42cab847-8f5e-4b6d-ba03-16633e22656e",
          "length": 6,
          "cycles": 1,
          "position": 5,
          "iteration": 0,
          "httpRequestId": "2efd3226-7083-48c0-83b7-03ac540c2bc1"
        },
        "item": {
          "id": "743b51f6-a421-4a11-b1ff-ad79ac79591e",
          "name": "Verify Revocation"
        },
        "response": {},
        "assertions": [
          {
            "assertion": "`access_token` collection variable must be set",
            "skipped": false
          },
          {
            "assertion": "`verifiable_credential` collection variable must be set",
            "skipped": false
          },
          {
            "assertion": "must return `200 Success` status",
            "skipped": false,
            "error": {
              "name": "AssertionError",
              "index": 2,
              "test": "must return `200 Success` status",
              "message": "expected { Object (id, _details, ...) } to have property 'code'",
              "stack": "AssertionError: expected { Object (id, _details, ...) } to have property 'code'\n   at Object.eval sandbox-script.js:3:6)"
            }
          },
          {
            "assertion": "Checks should have credentialStatus errors",
            "skipped": false,
            "error": {
              "name": "JSONError",
              "index": 3,
              "test": "Checks should have credentialStatus errors",
              "message": "Unexpected token u in JSON at position 0",
              "stack": "JSONError: Unexpected token u in JSON at position 0\n   at Object.eval sandbox-script.js:4:6)"
            }
          }
        ]
      }
    ]
  }
}